TriangleStrategy/Environment.py
TriangleStrategy/ModelArchitecture.py
TriangleStrategy/TrainFunctions.py
TriangleStrategy/__init__.py
TriangleStrategy/Methods/A2C.py
TriangleStrategy/Methods/DDPG.py
TriangleStrategy/Methods/DQN.py
TriangleStrategy/Methods/DQNA.py
TriangleStrategy/Methods/OASS.py
TriangleStrategy/Methods/PG.py
TriangleStrategy/Methods/PPO.py
TriangleStrategy/Methods/__init__.py
TriangleStrategy-1.0.1.dist-info/METADATA
TriangleStrategy-1.0.1.dist-info/WHEEL
TriangleStrategy-1.0.1.dist-info/top_level.txt
TriangleStrategy-1.0.1.dist-info/RECORD
