Metadata-Version: 2.1
Name: TriangleStrategy
Version: 1.0.1
Summary: TriangleStrategy is a high-efficiency reinforcement learning based algorithmic trading library.
Home-page: https://github.com/ECNU-CILAB/TriangleStrategy
Author: Artiprocher
Author-email: zjduan@stu.ecnu.edu.cn
License: UNKNOWN
Platform: UNKNOWN
